pywavi/__init__.py
pywavi/core/__init__.py
pywavi/core/flanker.py
pywavi/core/key.py
pywavi/core/patient.py
pywavi/core/pthree.py
pywavi/util/__init__.py
pywavi/util/parse.py
pywavi-0.0.0.dev0.dist-info/LICENSE
pywavi-0.0.0.dev0.dist-info/METADATA
pywavi-0.0.0.dev0.dist-info/WHEEL
pywavi-0.0.0.dev0.dist-info/top_level.txt
pywavi-0.0.0.dev0.dist-info/RECORD
