Metadata-Version: 2.1
Name: pywavi
Version: 0.0.0-DEV-
Summary: WAVI data analysis in python
Author: raceee
Author-email: <rcpeterson@noordacom.org>
Keywords: python,eeg,neurology,datascience,machine learning
Classifier: Development Status :: 1 - Planning
Classifier: Intended Audience :: Developers
Classifier: Programming Language :: Python :: 3
Classifier: Operating System :: Unix
Classifier: Operating System :: MacOS :: MacOS X
Classifier: Operating System :: Microsoft :: Windows
License-File: LICENSE
Requires-Dist: numpy
Requires-Dist: scipy
Requires-Dist: scikit-learn
Requires-Dist: matplotlib
Requires-Dist: pandas
